{"nodes": [{"id": "spec_intro_narrative", "label": "Intro & Narrative Spec (\u00a723)", "file_type": "document", "source_file": "docs/spec/intro-narrative.md", "source_location": null, "source_url": null, "captured_at": null, "author": null, "contributor": null}, {"id": "concept_intro_sequence", "label": "Intro Sequence Animation", "file_type": "concept", "source_file": "docs/spec/intro-narrative.md", "source_location": "\u00a723.1", "source_url": null, "captured_at": null, "author": null, "contributor": null}, {"id": "concept_copy_protection", "label": "Copy Protection (Riddle + Disk Timestamp)", "file_type": "concept", "source_file": "docs/spec/intro-narrative.md", "source_location": "\u00a723.2", "source_url": null, "captured_at": null, "author": null, "contributor": null}, {"id": "concept_scroll_area_text", "label": "Scroll Area Message Provenance Invariant", "file_type": "rationale", "source_file": "docs/spec/intro-narrative.md", "source_location": "\u00a723.6", "source_url": null, "captured_at": null, "author": null, "contributor": null, "rationale": "Every string reaching the HI scroll area must originate from narr.asm tables (faery.toml [narr]) or hardcoded literals from dialog_system.md. No new player-facing prose may be invented in Rust code \u2014 this is a fidelity invariant enforced by R-INTRO-012/013/014."}, {"id": "concept_ssp_scrolling_print", "label": "ssp (Scrolling String Print)", "file_type": "concept", "source_file": "docs/spec/intro-narrative.md", "source_location": "\u00a723.5", "source_url": null, "captured_at": null, "author": null, "contributor": null}, {"id": "concept_extract_template", "label": "extract() Template Engine (% substitution)", "file_type": "concept", "source_file": "docs/spec/intro-narrative.md", "source_location": "\u00a723.5", "source_url": null, "captured_at": null, "author": null, "contributor": null}], "edges": [{"source": "spec_intro_narrative", "target": "concept_intro_sequence", "relation": "references", "confidence": "EXTRACTED", "confidence_score": 1.0, "source_file": "docs/spec/intro-narrative.md", "source_location": "\u00a723.1", "weight": 1.0}, {"source": "spec_intro_narrative", "target": "concept_copy_protection", "relation": "references", "confidence": "EXTRACTED", "confidence_score": 1.0, "source_file": "docs/spec/intro-narrative.md", "source_location": "\u00a723.2", "weight": 1.0}, {"source": "spec_intro_narrative", "target": "concept_scroll_area_text", "relation": "references", "confidence": "EXTRACTED", "confidence_score": 1.0, "source_file": "docs/spec/intro-narrative.md", "source_location": "\u00a723.6", "weight": 1.0}, {"source": "spec_intro_narrative", "target": "concept_ssp_scrolling_print", "relation": "references", "confidence": "EXTRACTED", "confidence_score": 1.0, "source_file": "docs/spec/intro-narrative.md", "source_location": "\u00a723.5", "weight": 1.0}, {"source": "spec_intro_narrative", "target": "concept_extract_template", "relation": "references", "confidence": "EXTRACTED", "confidence_score": 1.0, "source_file": "docs/spec/intro-narrative.md", "source_location": "\u00a723.5", "weight": 1.0}, {"source": "concept_scroll_area_text", "target": "spec_intro_narrative", "relation": "rationale_for", "confidence": "EXTRACTED", "confidence_score": 1.0, "source_file": "docs/spec/intro-narrative.md", "source_location": "\u00a723.6", "weight": 1.0}], "hyperedges": []}