{"nodes": [{"id": "spec_save_load", "label": "Save/Load System Spec (\u00a724)", "file_type": "document", "source_file": "docs/spec/save-load.md", "source_location": null, "source_url": null, "captured_at": null, "author": null, "contributor": null}, {"id": "concept_save_format", "label": "Save File Format (raw binary, 8 slots A-H)", "file_type": "concept", "source_file": "docs/spec/save-load.md", "source_location": "\u00a724.1-24.2", "source_url": null, "captured_at": null, "author": null, "contributor": null}, {"id": "concept_80byte_misc_block", "label": "80-Byte Misc Variables Save Block", "file_type": "concept", "source_file": "docs/spec/save-load.md", "source_location": "\u00a724.3", "source_url": null, "captured_at": null, "author": null, "contributor": null}], "edges": [{"source": "spec_save_load", "target": "concept_save_format", "relation": "references", "confidence": "EXTRACTED", "confidence_score": 1.0, "source_file": "docs/spec/save-load.md", "source_location": "\u00a724.1", "weight": 1.0}, {"source": "spec_save_load", "target": "concept_80byte_misc_block", "relation": "references", "confidence": "EXTRACTED", "confidence_score": 1.0, "source_file": "docs/spec/save-load.md", "source_location": "\u00a724.3", "weight": 1.0}, {"source": "concept_80byte_misc_block", "target": "concept_magic_timers", "relation": "shares_data_with", "confidence": "EXTRACTED", "confidence_score": 1.0, "source_file": "docs/spec/save-load.md", "source_location": "\u00a724.3", "weight": 1.0}, {"source": "concept_80byte_misc_block", "target": "concept_cheat1_debug", "relation": "shares_data_with", "confidence": "EXTRACTED", "confidence_score": 1.0, "source_file": "docs/spec/save-load.md", "source_location": "\u00a724.3", "weight": 1.0}], "hyperedges": []}