{"nodes": [{"id": "plans_ecs_plan_b", "label": "ECS Plan B: Components and Resources", "file_type": "document", "source_file": "docs/superpowers/plans/2025-01-01-ecs-plan-b-components.md", "source_location": null, "source_url": null, "captured_at": null, "author": null, "contributor": null}, {"id": "concept_ecs_components", "label": "ECS Component Types (Position, Facing, HeroStats, etc.)", "file_type": "concept", "source_file": "docs/superpowers/plans/2025-01-01-ecs-plan-b-components.md", "source_location": "Task 2", "source_url": null, "captured_at": null, "author": null, "contributor": null}, {"id": "concept_ecs_resources", "label": "ECS Resources Struct (GameClock, RegionState, etc.)", "file_type": "concept", "source_file": "docs/superpowers/plans/2025-01-01-ecs-plan-b-components.md", "source_location": "Task 3", "source_url": null, "captured_at": null, "author": null, "contributor": null}, {"id": "concept_ecs_events", "label": "ECS Events Queue (DamageEvent, EnemyDiedEvent, etc.)", "file_type": "concept", "source_file": "docs/superpowers/plans/2025-01-01-ecs-plan-b-components.md", "source_location": "Task 4", "source_url": null, "captured_at": null, "author": null, "contributor": null}, {"id": "concept_ecs_spawn_helpers", "label": "ECS Spawn Helper Functions (spawn_hero, spawn_enemy, etc.)", "file_type": "concept", "source_file": "docs/superpowers/plans/2025-01-01-ecs-plan-b-components.md", "source_location": "Task 5", "source_url": null, "captured_at": null, "author": null, "contributor": null}], "edges": [{"source": "plans_ecs_plan_b", "target": "concept_ecs_components", "relation": "references", "confidence": "EXTRACTED", "confidence_score": 1.0, "source_file": "docs/superpowers/plans/2025-01-01-ecs-plan-b-components.md", "source_location": "Task 2", "weight": 1.0}, {"source": "plans_ecs_plan_b", "target": "concept_ecs_resources", "relation": "references", "confidence": "EXTRACTED", "confidence_score": 1.0, "source_file": "docs/superpowers/plans/2025-01-01-ecs-plan-b-components.md", "source_location": "Task 3", "weight": 1.0}, {"source": "plans_ecs_plan_b", "target": "concept_ecs_events", "relation": "references", "confidence": "EXTRACTED", "confidence_score": 1.0, "source_file": "docs/superpowers/plans/2025-01-01-ecs-plan-b-components.md", "source_location": "Task 4", "weight": 1.0}, {"source": "plans_ecs_plan_b", "target": "concept_ecs_spawn_helpers", "relation": "references", "confidence": "EXTRACTED", "confidence_score": 1.0, "source_file": "docs/superpowers/plans/2025-01-01-ecs-plan-b-components.md", "source_location": "Task 5", "weight": 1.0}, {"source": "plans_ecs_plan_b", "target": "plans_ecs_plan_a", "relation": "references", "confidence": "EXTRACTED", "confidence_score": 1.0, "source_file": "docs/superpowers/plans/2025-01-01-ecs-plan-b-components.md", "source_location": "Prerequisites", "weight": 1.0}, {"source": "concept_ecs_components", "target": "concept_inventory_structure", "relation": "implements", "confidence": "INFERRED", "confidence_score": 0.95, "source_file": "docs/superpowers/plans/2025-01-01-ecs-plan-b-components.md", "source_location": "Task 2", "weight": 0.95}, {"source": "concept_ecs_resources", "target": "concept_magic_timers", "relation": "shares_data_with", "confidence": "INFERRED", "confidence_score": 0.95, "source_file": "docs/superpowers/plans/2025-01-01-ecs-plan-b-components.md", "source_location": "Task 3 \u2014 GameClock", "weight": 0.95}, {"source": "concept_ecs_events", "target": "concept_ecs_system_schedule", "relation": "shares_data_with", "confidence": "INFERRED", "confidence_score": 0.95, "source_file": "docs/superpowers/plans/2025-01-01-ecs-plan-b-components.md", "source_location": "Task 4", "weight": 0.95}], "hyperedges": [{"id": "ecs_migration_chain", "label": "ECS Migration Plan Dependency Chain (A\u2192B\u2192C\u2192D)", "nodes": ["plans_ecs_plan_a", "plans_ecs_plan_b", "plans_ecs_plan_c", "plans_ecs_plan_d"], "relation": "form", "confidence": "EXTRACTED", "confidence_score": 1.0, "source_file": "docs/superpowers/plans/2025-01-01-ecs-plan-b-components.md"}]}