{"nodes": [{"id": "home_ddehaven_projects_faery_tale_rs_src_game_npc_rs", "label": "npc.rs", "file_type": "code", "source_file": "src/game/npc.rs", "source_location": "L1"}, {"id": "game_npc_npcstate", "label": "NpcState", "file_type": "code", "source_file": "src/game/npc.rs", "source_location": "L61"}, {"id": "game_npc_npc", "label": "Npc", "file_type": "code", "source_file": "src/game/npc.rs", "source_location": "L74"}, {"id": "goal", "label": "Goal", "file_type": "code", "source_file": "src/game/npc.rs", "source_location": "L84"}, {"id": "tactic", "label": "Tactic", "file_type": "code", "source_file": "src/game/npc.rs", "source_location": "L85"}, {"id": "direction", "label": "Direction", "file_type": "code", "source_file": "src/game/npc.rs", "source_location": "L86"}, {"id": "game_npc_npc_from_bytes", "label": ".from_bytes()", "file_type": "code", "source_file": "src/game/npc.rs", "source_location": "L102"}, {"id": "self", "label": "Self", "file_type": "code", "source_file": "src/game/npc.rs", "source_location": "L102"}, {"id": "game_npc_npc_tick", "label": ".tick()", "file_type": "code", "source_file": "src/game/npc.rs", "source_location": "L130"}, {"id": "option", "label": "Option", "file_type": "code", "source_file": "src/game/npc.rs", "source_location": "L130"}, {"id": "worlddata", "label": "WorldData", "file_type": "code", "source_file": "src/game/npc.rs", "source_location": "L130"}, {"id": "game_npc_npc_tick_with_actors", "label": ".tick_with_actors()", "file_type": "code", "source_file": "src/game/npc.rs", "source_location": "L143"}, {"id": "game_npc_npc_defeat", "label": ".defeat()", "file_type": "code", "source_file": "src/game/npc.rs", "source_location": "L209"}, {"id": "game_npc_npc_mark_dead", "label": ".mark_dead()", "file_type": "code", "source_file": "src/game/npc.rs", "source_location": "L221"}, {"id": "game_npc_npc_slot_free", "label": ".slot_free()", "file_type": "code", "source_file": "src/game/npc.rs", "source_location": "L232"}, {"id": "game_npc_npctable", "label": "NpcTable", "file_type": "code", "source_file": "src/game/npc.rs", "source_location": "L243"}, {"id": "game_npc_npctable_load", "label": ".load()", "file_type": "code", "source_file": "src/game/npc.rs", "source_location": "L248"}, {"id": "adfdisk", "label": "AdfDisk", "file_type": "code", "source_file": "src/game/npc.rs", "source_location": "L248"}, {"id": "game_npc_npctable_active_count", "label": ".active_count()", "file_type": "code", "source_file": "src/game/npc.rs", "source_location": "L264"}, {"id": "game_npc_test_npc_from_zero_bytes", "label": "test_npc_from_zero_bytes()", "file_type": "code", "source_file": "src/game/npc.rs", "source_location": "L275"}, {"id": "game_npc_test_npc_table_load", "label": "test_npc_table_load()", "file_type": "code", "source_file": "src/game/npc.rs", "source_location": "L283"}, {"id": "game_npc_test_npc_from_bytes_human", "label": "test_npc_from_bytes_human()", "file_type": "code", "source_file": "src/game/npc.rs", "source_location": "L290"}, {"id": "game_npc_test_npc_tick_chase", "label": "test_npc_tick_chase()", "file_type": "code", "source_file": "src/game/npc.rs", "source_location": "L303"}, {"id": "game_npc_test_npc_tick_moves_toward_hero_with_direction_lut", "label": "test_npc_tick_moves_toward_hero_with_direction_lut()", "file_type": "code", "source_file": "src/game/npc.rs", "source_location": "L322"}, {"id": "game_npc_test_npc_defeat", "label": "test_npc_defeat()", "file_type": "code", "source_file": "src/game/npc.rs", "source_location": "L342"}, {"id": "game_npc_test_npc_ai_fields_default", "label": "test_npc_ai_fields_default()", "file_type": "code", "source_file": "src/game/npc.rs", "source_location": "L355"}, {"id": "game_npc_test_npc_tick_uses_stored_facing", "label": "test_npc_tick_uses_stored_facing()", "file_type": "code", "source_file": "src/game/npc.rs", "source_location": "L365"}, {"id": "game_npc_test_npc_tick_still_does_not_move", "label": "test_npc_tick_still_does_not_move()", "file_type": "code", "source_file": "src/game/npc.rs", "source_location": "L383"}, {"id": "game_npc_test_npc_tick_blocked_becomes_frust", "label": "test_npc_tick_blocked_becomes_frust()", "file_type": "code", "source_file": "src/game/npc.rs", "source_location": "L403"}, {"id": "game_npc_test_npc_tick_blocked_by_actor", "label": "test_npc_tick_blocked_by_actor()", "file_type": "code", "source_file": "src/game/npc.rs", "source_location": "L421"}, {"id": "game_npc_test_npc_tick_not_blocked_by_distant_actor", "label": "test_npc_tick_not_blocked_by_distant_actor()", "file_type": "code", "source_file": "src/game/npc.rs", "source_location": "L446"}, {"id": "game_npc_test_npc_tick_empty_actors_same_as_no_actors", "label": "test_npc_tick_empty_actors_same_as_no_actors()", "file_type": "code", "source_file": "src/game/npc.rs", "source_location": "L465"}, {"id": "game_npc_blocked_east_npc", "label": "blocked_east_npc()", "file_type": "code", "source_file": "src/game/npc.rs", "source_location": "L487"}, {"id": "vec", "label": "Vec", "file_type": "code", "source_file": "src/game/npc.rs", "source_location": "L487"}, {"id": "game_npc_test_blocked_npc_sets_tactic_frust_and_still", "label": "test_blocked_npc_sets_tactic_frust_and_still()", "file_type": "code", "source_file": "src/game/npc.rs", "source_location": "L504"}, {"id": "game_npc_test_deviation_move_clears_frust_tactic", "label": "test_deviation_move_clears_frust_tactic()", "file_type": "code", "source_file": "src/game/npc.rs", "source_location": "L516"}, {"id": "game_npc_test_npc_speed_for_terrain_chain", "label": "test_npc_speed_for_terrain_chain()", "file_type": "code", "source_file": "src/game/npc.rs", "source_location": "L539"}, {"id": "game_npc_test_wraith_and_snake_ignore_terrain_speed", "label": "test_wraith_and_snake_ignore_terrain_speed()", "file_type": "code", "source_file": "src/game/npc.rs", "source_location": "L550"}], "edges": [{"source": "home_ddehaven_projects_faery_tale_rs_src_game_npc_rs", "target": "actor", "relation": "imports_from", "confidence": "EXTRACTED", "source_file": "src/game/npc.rs", "source_location": "L4", "weight": 1.0, "context": "import"}, {"source": "home_ddehaven_projects_faery_tale_rs_src_game_npc_rs", "target": "adfdisk", "relation": "imports_from", "confidence": "EXTRACTED", "source_file": "src/game/npc.rs", "source_location": "L5", "weight": 1.0, "context": "import"}, {"source": "home_ddehaven_projects_faery_tale_rs_src_game_npc_rs", "target": "direction", "relation": "imports_from", "confidence": "EXTRACTED", "source_file": "src/game/npc.rs", "source_location": "L6", "weight": 1.0, "context": "import"}, {"source": "home_ddehaven_projects_faery_tale_rs_src_game_npc_rs", "target": "game_npc_npcstate", "relation": "contains", "confidence": "EXTRACTED", "source_file": "src/game/npc.rs", "source_location": "L61", "weight": 1.0}, {"source": "home_ddehaven_projects_faery_tale_rs_src_game_npc_rs", "target": "game_npc_npc", "relation": "contains", "confidence": "EXTRACTED", "source_file": "src/game/npc.rs", "source_location": "L74", "weight": 1.0}, {"source": "game_npc_npc", "target": "goal", "relation": "references", "confidence": "EXTRACTED", "source_file": "src/game/npc.rs", "source_location": "L84", "weight": 1.0, "context": "field"}, {"source": "game_npc_npc", "target": "tactic", "relation": "references", "confidence": "EXTRACTED", "source_file": "src/game/npc.rs", "source_location": "L85", "weight": 1.0, "context": "field"}, {"source": "game_npc_npc", "target": "direction", "relation": "references", "confidence": "EXTRACTED", "source_file": "src/game/npc.rs", "source_location": "L86", "weight": 1.0, "context": "field"}, {"source": "game_npc_npc", "target": "game_npc_npcstate", "relation": "references", "confidence": "EXTRACTED", "source_file": "src/game/npc.rs", "source_location": "L87", "weight": 1.0, "context": "field"}, {"source": "game_npc_npc", "target": "game_npc_npc_from_bytes", "relation": "method", "confidence": "EXTRACTED", "source_file": "src/game/npc.rs", "source_location": "L102", "weight": 1.0}, {"source": "game_npc_npc_from_bytes", "target": "self", "relation": "references", "confidence": "EXTRACTED", "source_file": "src/game/npc.rs", "source_location": "L102", "weight": 1.0, "context": "return_type"}, {"source": "game_npc_npc", "target": "game_npc_npc_tick", "relation": "method", "confidence": "EXTRACTED", "source_file": "src/game/npc.rs", "source_location": "L130", "weight": 1.0}, {"source": "game_npc_npc_tick", "target": "option", "relation": "references", "confidence": "EXTRACTED", "source_file": "src/game/npc.rs", "source_location": "L130", "weight": 1.0, "context": "parameter_type"}, {"source": "game_npc_npc_tick", "target": "worlddata", "relation": "references", "confidence": "EXTRACTED", "source_file": "src/game/npc.rs", "source_location": "L130", "weight": 1.0, "context": "generic_arg"}, {"source": "game_npc_npc", "target": "game_npc_npc_tick_with_actors", "relation": "method", "confidence": "EXTRACTED", "source_file": "src/game/npc.rs", "source_location": "L143", "weight": 1.0}, {"source": "game_npc_npc_tick_with_actors", "target": "option", "relation": "references", "confidence": "EXTRACTED", "source_file": "src/game/npc.rs", "source_location": "L143", "weight": 1.0, "context": "parameter_type"}, {"source": "game_npc_npc_tick_with_actors", "target": "worlddata", "relation": "references", "confidence": "EXTRACTED", "source_file": "src/game/npc.rs", "source_location": "L143", "weight": 1.0, "context": "generic_arg"}, {"source": "game_npc_npc", "target": "game_npc_npc_defeat", "relation": "method", "confidence": "EXTRACTED", "source_file": "src/game/npc.rs", "source_location": "L209", "weight": 1.0}, {"source": "game_npc_npc", "target": "game_npc_npc_mark_dead", "relation": "method", "confidence": "EXTRACTED", "source_file": "src/game/npc.rs", "source_location": "L221", "weight": 1.0}, {"source": "game_npc_npc", "target": "game_npc_npc_slot_free", "relation": "method", "confidence": "EXTRACTED", "source_file": "src/game/npc.rs", "source_location": "L232", "weight": 1.0}, {"source": "home_ddehaven_projects_faery_tale_rs_src_game_npc_rs", "target": "game_npc_npctable", "relation": "contains", "confidence": "EXTRACTED", "source_file": "src/game/npc.rs", "source_location": "L243", "weight": 1.0}, {"source": "game_npc_npctable", "target": "game_npc_npc", "relation": "references", "confidence": "EXTRACTED", "source_file": "src/game/npc.rs", "source_location": "L244", "weight": 1.0, "context": "field"}, {"source": "game_npc_npctable", "target": "game_npc_npctable_load", "relation": "method", "confidence": "EXTRACTED", "source_file": "src/game/npc.rs", "source_location": "L248", "weight": 1.0}, {"source": "game_npc_npctable_load", "target": "adfdisk", "relation": "references", "confidence": "EXTRACTED", "source_file": "src/game/npc.rs", "source_location": "L248", "weight": 1.0, "context": "parameter_type"}, {"source": "game_npc_npctable_load", "target": "self", "relation": "references", "confidence": "EXTRACTED", "source_file": "src/game/npc.rs", "source_location": "L248", "weight": 1.0, "context": "return_type"}, {"source": "game_npc_npctable", "target": "game_npc_npctable_active_count", "relation": "method", "confidence": "EXTRACTED", "source_file": "src/game/npc.rs", "source_location": "L264", "weight": 1.0}, {"source": "home_ddehaven_projects_faery_tale_rs_src_game_npc_rs", "target": "super", "relation": "imports_from", "confidence": "EXTRACTED", "source_file": "src/game/npc.rs", "source_location": "L271", "weight": 1.0, "context": "import"}, {"source": "home_ddehaven_projects_faery_tale_rs_src_game_npc_rs", "target": "adfdisk", "relation": "imports_from", "confidence": "EXTRACTED", "source_file": "src/game/npc.rs", "source_location": "L272", "weight": 1.0, "context": "import"}, {"source": "home_ddehaven_projects_faery_tale_rs_src_game_npc_rs", "target": "game_npc_test_npc_from_zero_bytes", "relation": "contains", "confidence": "EXTRACTED", "source_file": "src/game/npc.rs", "source_location": "L275", "weight": 1.0}, {"source": "home_ddehaven_projects_faery_tale_rs_src_game_npc_rs", "target": "game_npc_test_npc_table_load", "relation": "contains", "confidence": "EXTRACTED", "source_file": "src/game/npc.rs", "source_location": "L283", "weight": 1.0}, {"source": "home_ddehaven_projects_faery_tale_rs_src_game_npc_rs", "target": "game_npc_test_npc_from_bytes_human", "relation": "contains", "confidence": "EXTRACTED", "source_file": "src/game/npc.rs", "source_location": "L290", "weight": 1.0}, {"source": "home_ddehaven_projects_faery_tale_rs_src_game_npc_rs", "target": "game_npc_test_npc_tick_chase", "relation": "contains", "confidence": "EXTRACTED", "source_file": "src/game/npc.rs", "source_location": "L303", "weight": 1.0}, {"source": "home_ddehaven_projects_faery_tale_rs_src_game_npc_rs", "target": "game_npc_test_npc_tick_moves_toward_hero_with_direction_lut", "relation": "contains", "confidence": "EXTRACTED", "source_file": "src/game/npc.rs", "source_location": "L322", "weight": 1.0}, {"source": "home_ddehaven_projects_faery_tale_rs_src_game_npc_rs", "target": "game_npc_test_npc_defeat", "relation": "contains", "confidence": "EXTRACTED", "source_file": "src/game/npc.rs", "source_location": "L342", "weight": 1.0}, {"source": "home_ddehaven_projects_faery_tale_rs_src_game_npc_rs", "target": "game_npc_test_npc_ai_fields_default", "relation": "contains", "confidence": "EXTRACTED", "source_file": "src/game/npc.rs", "source_location": "L355", "weight": 1.0}, {"source": "home_ddehaven_projects_faery_tale_rs_src_game_npc_rs", "target": "game_npc_test_npc_tick_uses_stored_facing", "relation": "contains", "confidence": "EXTRACTED", "source_file": "src/game/npc.rs", "source_location": "L365", "weight": 1.0}, {"source": "home_ddehaven_projects_faery_tale_rs_src_game_npc_rs", "target": "game_npc_test_npc_tick_still_does_not_move", "relation": "contains", "confidence": "EXTRACTED", "source_file": "src/game/npc.rs", "source_location": "L383", "weight": 1.0}, {"source": "home_ddehaven_projects_faery_tale_rs_src_game_npc_rs", "target": "game_npc_test_npc_tick_blocked_becomes_frust", "relation": "contains", "confidence": "EXTRACTED", "source_file": "src/game/npc.rs", "source_location": "L403", "weight": 1.0}, {"source": "home_ddehaven_projects_faery_tale_rs_src_game_npc_rs", "target": "game_npc_test_npc_tick_blocked_by_actor", "relation": "contains", "confidence": "EXTRACTED", "source_file": "src/game/npc.rs", "source_location": "L421", "weight": 1.0}, {"source": "home_ddehaven_projects_faery_tale_rs_src_game_npc_rs", "target": "game_npc_test_npc_tick_not_blocked_by_distant_actor", "relation": "contains", "confidence": "EXTRACTED", "source_file": "src/game/npc.rs", "source_location": "L446", "weight": 1.0}, {"source": "home_ddehaven_projects_faery_tale_rs_src_game_npc_rs", "target": "game_npc_test_npc_tick_empty_actors_same_as_no_actors", "relation": "contains", "confidence": "EXTRACTED", "source_file": "src/game/npc.rs", "source_location": "L465", "weight": 1.0}, {"source": "home_ddehaven_projects_faery_tale_rs_src_game_npc_rs", "target": "game_npc_blocked_east_npc", "relation": "contains", "confidence": "EXTRACTED", "source_file": "src/game/npc.rs", "source_location": "L487", "weight": 1.0}, {"source": "game_npc_blocked_east_npc", "target": "game_npc_npc", "relation": "references", "confidence": "EXTRACTED", "source_file": "src/game/npc.rs", "source_location": "L487", "weight": 1.0, "context": "return_type"}, {"source": "game_npc_blocked_east_npc", "target": "vec", "relation": "references", "confidence": "EXTRACTED", "source_file": "src/game/npc.rs", "source_location": "L487", "weight": 1.0, "context": "return_type"}, {"source": "home_ddehaven_projects_faery_tale_rs_src_game_npc_rs", "target": "game_npc_test_blocked_npc_sets_tactic_frust_and_still", "relation": "contains", "confidence": "EXTRACTED", "source_file": "src/game/npc.rs", "source_location": "L504", "weight": 1.0}, {"source": "home_ddehaven_projects_faery_tale_rs_src_game_npc_rs", "target": "game_npc_test_deviation_move_clears_frust_tactic", "relation": "contains", "confidence": "EXTRACTED", "source_file": "src/game/npc.rs", "source_location": "L516", "weight": 1.0}, {"source": "home_ddehaven_projects_faery_tale_rs_src_game_npc_rs", "target": "game_npc_test_npc_speed_for_terrain_chain", "relation": "contains", "confidence": "EXTRACTED", "source_file": "src/game/npc.rs", "source_location": "L539", "weight": 1.0}, {"source": "home_ddehaven_projects_faery_tale_rs_src_game_npc_rs", "target": "game_npc_test_wraith_and_snake_ignore_terrain_speed", "relation": "contains", "confidence": "EXTRACTED", "source_file": "src/game/npc.rs", "source_location": "L550", "weight": 1.0}, {"source": "game_npc_npc_tick", "target": "game_npc_npc_tick_with_actors", "relation": "calls", "context": "call", "confidence": "EXTRACTED", "source_file": "src/game/npc.rs", "source_location": "L131", "weight": 1.0}, {"source": "game_npc_npctable_load", "target": "game_npc_npc_from_bytes", "relation": "calls", "context": "call", "confidence": "EXTRACTED", "source_file": "src/game/npc.rs", "source_location": "L257", "weight": 1.0}, {"source": "game_npc_test_npc_from_zero_bytes", "target": "game_npc_npc_from_bytes", "relation": "calls", "context": "call", "confidence": "EXTRACTED", "source_file": "src/game/npc.rs", "source_location": "L277", "weight": 1.0}, {"source": "game_npc_test_npc_table_load", "target": "game_npc_npc_from_bytes", "relation": "calls", "context": "call", "confidence": "EXTRACTED", "source_file": "src/game/npc.rs", "source_location": "L284", "weight": 1.0}, {"source": "game_npc_test_npc_table_load", "target": "game_npc_npctable_load", "relation": "calls", "context": "call", "confidence": "EXTRACTED", "source_file": "src/game/npc.rs", "source_location": "L285", "weight": 1.0}, {"source": "game_npc_test_npc_from_bytes_human", "target": "game_npc_npc_from_bytes", "relation": "calls", "context": "call", "confidence": "EXTRACTED", "source_file": "src/game/npc.rs", "source_location": "L296", "weight": 1.0}, {"source": "game_npc_test_npc_tick_chase", "target": "game_npc_npc_tick", "relation": "calls", "context": "call", "confidence": "EXTRACTED", "source_file": "src/game/npc.rs", "source_location": "L317", "weight": 1.0}, {"source": "game_npc_test_npc_tick_moves_toward_hero_with_direction_lut", "target": "game_npc_npc_tick", "relation": "calls", "context": "call", "confidence": "EXTRACTED", "source_file": "src/game/npc.rs", "source_location": "L337", "weight": 1.0}, {"source": "game_npc_test_npc_defeat", "target": "game_npc_npc_defeat", "relation": "calls", "context": "call", "confidence": "EXTRACTED", "source_file": "src/game/npc.rs", "source_location": "L349", "weight": 1.0}, {"source": "game_npc_test_npc_tick_uses_stored_facing", "target": "game_npc_npc_tick", "relation": "calls", "context": "call", "confidence": "EXTRACTED", "source_file": "src/game/npc.rs", "source_location": "L378", "weight": 1.0}, {"source": "game_npc_test_npc_tick_still_does_not_move", "target": "game_npc_npc_tick", "relation": "calls", "context": "call", "confidence": "EXTRACTED", "source_file": "src/game/npc.rs", "source_location": "L397", "weight": 1.0}, {"source": "game_npc_test_npc_tick_blocked_becomes_frust", "target": "game_npc_npc_tick", "relation": "calls", "context": "call", "confidence": "EXTRACTED", "source_file": "src/game/npc.rs", "source_location": "L416", "weight": 1.0}, {"source": "game_npc_test_npc_tick_blocked_by_actor", "target": "game_npc_npc_tick_with_actors", "relation": "calls", "context": "call", "confidence": "EXTRACTED", "source_file": "src/game/npc.rs", "source_location": "L438", "weight": 1.0}, {"source": "game_npc_test_npc_tick_not_blocked_by_distant_actor", "target": "game_npc_npc_tick_with_actors", "relation": "calls", "context": "call", "confidence": "EXTRACTED", "source_file": "src/game/npc.rs", "source_location": "L460", "weight": 1.0}, {"source": "game_npc_test_npc_tick_empty_actors_same_as_no_actors", "target": "game_npc_npc_tick", "relation": "calls", "context": "call", "confidence": "EXTRACTED", "source_file": "src/game/npc.rs", "source_location": "L478", "weight": 1.0}, {"source": "game_npc_test_npc_tick_empty_actors_same_as_no_actors", "target": "game_npc_npc_tick_with_actors", "relation": "calls", "context": "call", "confidence": "EXTRACTED", "source_file": "src/game/npc.rs", "source_location": "L479", "weight": 1.0}, {"source": "game_npc_test_blocked_npc_sets_tactic_frust_and_still", "target": "game_npc_blocked_east_npc", "relation": "calls", "context": "call", "confidence": "EXTRACTED", "source_file": "src/game/npc.rs", "source_location": "L509", "weight": 1.0}, {"source": "game_npc_test_blocked_npc_sets_tactic_frust_and_still", "target": "game_npc_npc_tick_with_actors", "relation": "calls", "context": "call", "confidence": "EXTRACTED", "source_file": "src/game/npc.rs", "source_location": "L510", "weight": 1.0}, {"source": "game_npc_test_deviation_move_clears_frust_tactic", "target": "game_npc_npc_tick_with_actors", "relation": "calls", "context": "call", "confidence": "EXTRACTED", "source_file": "src/game/npc.rs", "source_location": "L531", "weight": 1.0}], "raw_calls": [{"caller_nid": "game_npc_npc_tick_with_actors", "callee": "map_or", "is_member_call": true, "source_file": "/home/ddehaven/projects/faery-tale-rs/src/game/npc.rs", "source_location": "L161"}, {"caller_nid": "game_npc_npc_tick_with_actors", "callee": "px_to_terrain_type", "is_member_call": false, "source_file": "/home/ddehaven/projects/faery-tale-rs/src/game/npc.rs", "source_location": "L161"}, {"caller_nid": "game_npc_npc_tick_with_actors", "callee": "newx", "is_member_call": false, "source_file": "/home/ddehaven/projects/faery-tale-rs/src/game/npc.rs", "source_location": "L165"}, {"caller_nid": "game_npc_npc_tick_with_actors", "callee": "newy", "is_member_call": false, "source_file": "/home/ddehaven/projects/faery-tale-rs/src/game/npc.rs", "source_location": "L166"}, {"caller_nid": "game_npc_npc_tick_with_actors", "callee": "proxcheck", "is_member_call": false, "source_file": "/home/ddehaven/projects/faery-tale-rs/src/game/npc.rs", "source_location": "L170"}, {"caller_nid": "game_npc_npc_tick_with_actors", "callee": "actor_collides", "is_member_call": false, "source_file": "/home/ddehaven/projects/faery-tale-rs/src/game/npc.rs", "source_location": "L171"}, {"caller_nid": "game_npc_npc_tick_with_actors", "callee": "rotate_cw", "is_member_call": true, "source_file": "/home/ddehaven/projects/faery-tale-rs/src/game/npc.rs", "source_location": "L178"}, {"caller_nid": "game_npc_npc_tick_with_actors", "callee": "newx", "is_member_call": false, "source_file": "/home/ddehaven/projects/faery-tale-rs/src/game/npc.rs", "source_location": "L179"}, {"caller_nid": "game_npc_npc_tick_with_actors", "callee": "newy", "is_member_call": false, "source_file": "/home/ddehaven/projects/faery-tale-rs/src/game/npc.rs", "source_location": "L180"}, {"caller_nid": "game_npc_npc_tick_with_actors", "callee": "proxcheck", "is_member_call": false, "source_file": "/home/ddehaven/projects/faery-tale-rs/src/game/npc.rs", "source_location": "L181"}, {"caller_nid": "game_npc_npc_tick_with_actors", "callee": "actor_collides", "is_member_call": false, "source_file": "/home/ddehaven/projects/faery-tale-rs/src/game/npc.rs", "source_location": "L182"}, {"caller_nid": "game_npc_npc_tick_with_actors", "callee": "rotate_ccw", "is_member_call": true, "source_file": "/home/ddehaven/projects/faery-tale-rs/src/game/npc.rs", "source_location": "L187"}, {"caller_nid": "game_npc_npc_tick_with_actors", "callee": "newx", "is_member_call": false, "source_file": "/home/ddehaven/projects/faery-tale-rs/src/game/npc.rs", "source_location": "L188"}, {"caller_nid": "game_npc_npc_tick_with_actors", "callee": "newy", "is_member_call": false, "source_file": "/home/ddehaven/projects/faery-tale-rs/src/game/npc.rs", "source_location": "L189"}, {"caller_nid": "game_npc_npc_tick_with_actors", "callee": "proxcheck", "is_member_call": false, "source_file": "/home/ddehaven/projects/faery-tale-rs/src/game/npc.rs", "source_location": "L191"}, {"caller_nid": "game_npc_npc_tick_with_actors", "callee": "actor_collides", "is_member_call": false, "source_file": "/home/ddehaven/projects/faery-tale-rs/src/game/npc.rs", "source_location": "L192"}, {"caller_nid": "game_npc_npctable_load", "callee": "load_blocks", "is_member_call": true, "source_file": "/home/ddehaven/projects/faery-tale-rs/src/game/npc.rs", "source_location": "L251"}, {"caller_nid": "game_npc_npctable_active_count", "callee": "count", "is_member_call": true, "source_file": "/home/ddehaven/projects/faery-tale-rs/src/game/npc.rs", "source_location": "L265"}]}