{"nodes": [{"id": "home_ddehaven_projects_faery_tale_rs_src_bin_music_viz_rs", "label": "music_viz.rs", "file_type": "code", "source_file": "src/bin/music_viz.rs", "source_location": "L1"}, {"id": "bin_music_viz_instruments", "label": "Instruments", "file_type": "code", "source_file": "src/bin/music_viz.rs", "source_location": "L107"}, {"id": "bin_music_viz_instruments_load", "label": ".load()", "file_type": "code", "source_file": "src/bin/music_viz.rs", "source_location": "L113"}, {"id": "path", "label": "Path", "file_type": "code", "source_file": "src/bin/music_viz.rs", "source_location": "L113"}, {"id": "option", "label": "Option", "file_type": "code", "source_file": "src/bin/music_viz.rs", "source_location": "L113"}, {"id": "self", "label": "Self", "file_type": "code", "source_file": "src/bin/music_viz.rs", "source_location": "L113"}, {"id": "bin_music_viz_instruments_parse", "label": ".parse()", "file_type": "code", "source_file": "src/bin/music_viz.rs", "source_location": "L118"}, {"id": "bin_music_viz_voice", "label": "Voice", "file_type": "code", "source_file": "src/bin/music_viz.rs", "source_location": "L148"}, {"id": "bin_music_viz_voice_new", "label": ".new()", "file_type": "code", "source_file": "src/bin/music_viz.rs", "source_location": "L169"}, {"id": "bin_music_viz_voice_set_instrument_slot", "label": ".set_instrument_slot()", "file_type": "code", "source_file": "src/bin/music_viz.rs", "source_location": "L190"}, {"id": "bin_music_viz_voice_trigger_note", "label": ".trigger_note()", "file_type": "code", "source_file": "src/bin/music_viz.rs", "source_location": "L196"}, {"id": "bin_music_viz_voice_silence", "label": ".silence()", "file_type": "code", "source_file": "src/bin/music_viz.rs", "source_location": "L224"}, {"id": "bin_music_viz_voice_step_envelope", "label": ".step_envelope()", "file_type": "code", "source_file": "src/bin/music_viz.rs", "source_location": "L230"}, {"id": "bin_music_viz_voice_mix_stereo", "label": ".mix_stereo()", "file_type": "code", "source_file": "src/bin/music_viz.rs", "source_location": "L244"}, {"id": "bin_music_viz_seqstate", "label": "SeqState", "file_type": "code", "source_file": "src/bin/music_viz.rs", "source_location": "L306"}, {"id": "arc", "label": "Arc", "file_type": "code", "source_file": "src/bin/music_viz.rs", "source_location": "L311"}, {"id": "track", "label": "Track", "file_type": "code", "source_file": "src/bin/music_viz.rs", "source_location": "L311"}, {"id": "bin_music_viz_seqstate_new", "label": ".new()", "file_type": "code", "source_file": "src/bin/music_viz.rs", "source_location": "L317"}, {"id": "bin_music_viz_seqstate_play_score", "label": ".play_score()", "file_type": "code", "source_file": "src/bin/music_viz.rs", "source_location": "L329"}, {"id": "bin_music_viz_seqstate_vbl_tick", "label": ".vbl_tick()", "file_type": "code", "source_file": "src/bin/music_viz.rs", "source_location": "L353"}, {"id": "bin_music_viz_seqstate_tick_voice", "label": ".tick_voice()", "file_type": "code", "source_file": "src/bin/music_viz.rs", "source_location": "L363"}, {"id": "bin_music_viz_synthcallback", "label": "SynthCallback", "file_type": "code", "source_file": "src/bin/music_viz.rs", "source_location": "L440"}, {"id": "mutex", "label": "Mutex", "file_type": "code", "source_file": "src/bin/music_viz.rs", "source_location": "L441"}, {"id": "audiocallback", "label": "AudioCallback", "file_type": "code", "source_file": "src/bin/music_viz.rs", "source_location": "L445"}, {"id": "bin_music_viz_synthcallback_callback", "label": ".callback()", "file_type": "code", "source_file": "src/bin/music_viz.rs", "source_location": "L446"}, {"id": "audiostream", "label": "AudioStream", "file_type": "code", "source_file": "src/bin/music_viz.rs", "source_location": "L446"}, {"id": "bin_music_viz_pitch_name", "label": "pitch_name()", "file_type": "code", "source_file": "src/bin/music_viz.rs", "source_location": "L526"}, {"id": "string", "label": "String", "file_type": "code", "source_file": "src/bin/music_viz.rs", "source_location": "L526"}, {"id": "bin_music_viz_scheduledevent", "label": "ScheduledEvent", "file_type": "code", "source_file": "src/bin/music_viz.rs", "source_location": "L551"}, {"id": "bin_music_viz_trackvis", "label": "TrackVis", "file_type": "code", "source_file": "src/bin/music_viz.rs", "source_location": "L558"}, {"id": "vec", "label": "Vec", "file_type": "code", "source_file": "src/bin/music_viz.rs", "source_location": "L559"}, {"id": "bin_music_viz_trackvis_new", "label": ".new()", "file_type": "code", "source_file": "src/bin/music_viz.rs", "source_location": "L567"}, {"id": "bin_music_viz_trackvis_event_at", "label": ".event_at()", "file_type": "code", "source_file": "src/bin/music_viz.rs", "source_location": "L637"}, {"id": "bin_music_viz_app", "label": "App", "file_type": "code", "source_file": "src/bin/music_viz.rs", "source_location": "L672"}, {"id": "songlibrary", "label": "SongLibrary", "file_type": "code", "source_file": "src/bin/music_viz.rs", "source_location": "L673"}, {"id": "bin_music_viz_app_new", "label": ".new()", "file_type": "code", "source_file": "src/bin/music_viz.rs", "source_location": "L684"}, {"id": "bin_music_viz_app_make_tracks", "label": ".make_tracks()", "file_type": "code", "source_file": "src/bin/music_viz.rs", "source_location": "L703"}, {"id": "bin_music_viz_app_auto_scale", "label": ".auto_scale()", "file_type": "code", "source_file": "src/bin/music_viz.rs", "source_location": "L716"}, {"id": "bin_music_viz_app_switch_group", "label": ".switch_group()", "file_type": "code", "source_file": "src/bin/music_viz.rs", "source_location": "L731"}, {"id": "bin_music_viz_app_toggle_track", "label": ".toggle_track()", "file_type": "code", "source_file": "src/bin/music_viz.rs", "source_location": "L755"}, {"id": "bin_music_viz_app_set_tempo", "label": ".set_tempo()", "file_type": "code", "source_file": "src/bin/music_viz.rs", "source_location": "L761"}, {"id": "bin_music_viz_app_zoom_out", "label": ".zoom_out()", "file_type": "code", "source_file": "src/bin/music_viz.rs", "source_location": "L767"}, {"id": "bin_music_viz_app_zoom_in", "label": ".zoom_in()", "file_type": "code", "source_file": "src/bin/music_viz.rs", "source_location": "L770"}, {"id": "bin_music_viz_app_set_paused", "label": ".set_paused()", "file_type": "code", "source_file": "src/bin/music_viz.rs", "source_location": "L774"}, {"id": "bin_music_viz_app_step_tick", "label": ".step_tick()", "file_type": "code", "source_file": "src/bin/music_viz.rs", "source_location": "L782"}, {"id": "bin_music_viz_app_audio_pos", "label": ".audio_pos()", "file_type": "code", "source_file": "src/bin/music_viz.rs", "source_location": "L791"}, {"id": "bin_music_viz_instrument_name", "label": "instrument_name()", "file_type": "code", "source_file": "src/bin/music_viz.rs", "source_location": "L804"}, {"id": "bin_music_viz_render", "label": "render()", "file_type": "code", "source_file": "src/bin/music_viz.rs", "source_location": "L811"}, {"id": "stdout", "label": "Stdout", "file_type": "code", "source_file": "src/bin/music_viz.rs", "source_location": "L811"}, {"id": "result", "label": "Result", "file_type": "code", "source_file": "src/bin/music_viz.rs", "source_location": "L811"}, {"id": "bin_music_viz_pad_or_clip", "label": "pad_or_clip()", "file_type": "code", "source_file": "src/bin/music_viz.rs", "source_location": "L1002"}, {"id": "bin_music_viz_main", "label": "main()", "file_type": "code", "source_file": "src/bin/music_viz.rs", "source_location": "L1015"}, {"id": "box", "label": "Box", "file_type": "code", "source_file": "src/bin/music_viz.rs", "source_location": "L1015"}, {"id": "error", "label": "Error", "file_type": "code", "source_file": "src/bin/music_viz.rs", "source_location": "L1015"}], "edges": [{"source": "home_ddehaven_projects_faery_tale_rs_src_bin_music_viz_rs", "target": "songs", "relation": "imports_from", "confidence": "EXTRACTED", "source_file": "src/bin/music_viz.rs", "source_location": "L24", "weight": 1.0, "context": "import"}, {"source": "home_ddehaven_projects_faery_tale_rs_src_bin_music_viz_rs", "target": "io", "relation": "imports_from", "confidence": "EXTRACTED", "source_file": "src/bin/music_viz.rs", "source_location": "L34", "weight": 1.0, "context": "import"}, {"source": "home_ddehaven_projects_faery_tale_rs_src_bin_music_viz_rs", "target": "path", "relation": "imports_from", "confidence": "EXTRACTED", "source_file": "src/bin/music_viz.rs", "source_location": "L35", "weight": 1.0, "context": "import"}, {"source": "home_ddehaven_projects_faery_tale_rs_src_bin_music_viz_rs", "target": "sync", "relation": "imports_from", "confidence": "EXTRACTED", "source_file": "src/bin/music_viz.rs", "source_location": "L36", "weight": 1.0, "context": "import"}, {"source": "home_ddehaven_projects_faery_tale_rs_src_bin_music_viz_rs", "target": "duration", "relation": "imports_from", "confidence": "EXTRACTED", "source_file": "src/bin/music_viz.rs", "source_location": "L37", "weight": 1.0, "context": "import"}, {"source": "home_ddehaven_projects_faery_tale_rs_src_bin_music_viz_rs", "target": "crossterm", "relation": "imports_from", "confidence": "EXTRACTED", "source_file": "src/bin/music_viz.rs", "source_location": "L39", "weight": 1.0, "context": "import"}, {"source": "home_ddehaven_projects_faery_tale_rs_src_bin_music_viz_rs", "target": "audio", "relation": "imports_from", "confidence": "EXTRACTED", "source_file": "src/bin/music_viz.rs", "source_location": "L47", "weight": 1.0, "context": "import"}, {"source": "home_ddehaven_projects_faery_tale_rs_src_bin_music_viz_rs", "target": "bin_music_viz_instruments", "relation": "contains", "confidence": "EXTRACTED", "source_file": "src/bin/music_viz.rs", "source_location": "L107", "weight": 1.0}, {"source": "bin_music_viz_instruments", "target": "bin_music_viz_instruments_load", "relation": "method", "confidence": "EXTRACTED", "source_file": "src/bin/music_viz.rs", "source_location": "L113", "weight": 1.0}, {"source": "bin_music_viz_instruments_load", "target": "path", "relation": "references", "confidence": "EXTRACTED", "source_file": "src/bin/music_viz.rs", "source_location": "L113", "weight": 1.0, "context": "parameter_type"}, {"source": "bin_music_viz_instruments_load", "target": "option", "relation": "references", "confidence": "EXTRACTED", "source_file": "src/bin/music_viz.rs", "source_location": "L113", "weight": 1.0, "context": "return_type"}, {"source": "bin_music_viz_instruments_load", "target": "self", "relation": "references", "confidence": "EXTRACTED", "source_file": "src/bin/music_viz.rs", "source_location": "L113", "weight": 1.0, "context": "generic_arg"}, {"source": "bin_music_viz_instruments", "target": "bin_music_viz_instruments_parse", "relation": "method", "confidence": "EXTRACTED", "source_file": "src/bin/music_viz.rs", "source_location": "L118", "weight": 1.0}, {"source": "bin_music_viz_instruments_parse", "target": "self", "relation": "references", "confidence": "EXTRACTED", "source_file": "src/bin/music_viz.rs", "source_location": "L118", "weight": 1.0, "context": "return_type"}, {"source": "home_ddehaven_projects_faery_tale_rs_src_bin_music_viz_rs", "target": "bin_music_viz_voice", "relation": "contains", "confidence": "EXTRACTED", "source_file": "src/bin/music_viz.rs", "source_location": "L148", "weight": 1.0}, {"source": "bin_music_viz_voice", "target": "option", "relation": "references", "confidence": "EXTRACTED", "source_file": "src/bin/music_viz.rs", "source_location": "L164", "weight": 1.0, "context": "field"}, {"source": "bin_music_viz_voice", "target": "option", "relation": "references", "confidence": "EXTRACTED", "source_file": "src/bin/music_viz.rs", "source_location": "L165", "weight": 1.0, "context": "field"}, {"source": "bin_music_viz_voice", "target": "bin_music_viz_voice_new", "relation": "method", "confidence": "EXTRACTED", "source_file": "src/bin/music_viz.rs", "source_location": "L169", "weight": 1.0}, {"source": "bin_music_viz_voice_new", "target": "self", "relation": "references", "confidence": "EXTRACTED", "source_file": "src/bin/music_viz.rs", "source_location": "L169", "weight": 1.0, "context": "return_type"}, {"source": "bin_music_viz_voice", "target": "bin_music_viz_voice_set_instrument_slot", "relation": "method", "confidence": "EXTRACTED", "source_file": "src/bin/music_viz.rs", "source_location": "L190", "weight": 1.0}, {"source": "bin_music_viz_voice", "target": "bin_music_viz_voice_trigger_note", "relation": "method", "confidence": "EXTRACTED", "source_file": "src/bin/music_viz.rs", "source_location": "L196", "weight": 1.0}, {"source": "bin_music_viz_voice_trigger_note", "target": "bin_music_viz_instruments", "relation": "references", "confidence": "EXTRACTED", "source_file": "src/bin/music_viz.rs", "source_location": "L196", "weight": 1.0, "context": "parameter_type"}, {"source": "bin_music_viz_voice", "target": "bin_music_viz_voice_silence", "relation": "method", "confidence": "EXTRACTED", "source_file": "src/bin/music_viz.rs", "source_location": "L224", "weight": 1.0}, {"source": "bin_music_viz_voice", "target": "bin_music_viz_voice_step_envelope", "relation": "method", "confidence": "EXTRACTED", "source_file": "src/bin/music_viz.rs", "source_location": "L230", "weight": 1.0}, {"source": "bin_music_viz_voice", "target": "bin_music_viz_voice_mix_stereo", "relation": "method", "confidence": "EXTRACTED", "source_file": "src/bin/music_viz.rs", "source_location": "L244", "weight": 1.0}, {"source": "bin_music_viz_voice_mix_stereo", "target": "bin_music_viz_instruments", "relation": "references", "confidence": "EXTRACTED", "source_file": "src/bin/music_viz.rs", "source_location": "L244", "weight": 1.0, "context": "parameter_type"}, {"source": "home_ddehaven_projects_faery_tale_rs_src_bin_music_viz_rs", "target": "bin_music_viz_seqstate", "relation": "contains", "confidence": "EXTRACTED", "source_file": "src/bin/music_viz.rs", "source_location": "L306", "weight": 1.0}, {"source": "bin_music_viz_seqstate", "target": "bin_music_viz_voice", "relation": "references", "confidence": "EXTRACTED", "source_file": "src/bin/music_viz.rs", "source_location": "L307", "weight": 1.0, "context": "field"}, {"source": "bin_music_viz_seqstate", "target": "option", "relation": "references", "confidence": "EXTRACTED", "source_file": "src/bin/music_viz.rs", "source_location": "L311", "weight": 1.0, "context": "field"}, {"source": "bin_music_viz_seqstate", "target": "arc", "relation": "references", "confidence": "EXTRACTED", "source_file": "src/bin/music_viz.rs", "source_location": "L311", "weight": 1.0, "context": "generic_arg"}, {"source": "bin_music_viz_seqstate", "target": "track", "relation": "references", "confidence": "EXTRACTED", "source_file": "src/bin/music_viz.rs", "source_location": "L311", "weight": 1.0, "context": "generic_arg"}, {"source": "bin_music_viz_seqstate", "target": "bin_music_viz_seqstate_new", "relation": "method", "confidence": "EXTRACTED", "source_file": "src/bin/music_viz.rs", "source_location": "L317", "weight": 1.0}, {"source": "bin_music_viz_seqstate_new", "target": "self", "relation": "references", "confidence": "EXTRACTED", "source_file": "src/bin/music_viz.rs", "source_location": "L317", "weight": 1.0, "context": "return_type"}, {"source": "bin_music_viz_seqstate", "target": "bin_music_viz_seqstate_play_score", "relation": "method", "confidence": "EXTRACTED", "source_file": "src/bin/music_viz.rs", "source_location": "L329", "weight": 1.0}, {"source": "bin_music_viz_seqstate_play_score", "target": "arc", "relation": "references", "confidence": "EXTRACTED", "source_file": "src/bin/music_viz.rs", "source_location": "L329", "weight": 1.0, "context": "parameter_type"}, {"source": "bin_music_viz_seqstate_play_score", "target": "track", "relation": "references", "confidence": "EXTRACTED", "source_file": "src/bin/music_viz.rs", "source_location": "L329", "weight": 1.0, "context": "generic_arg"}, {"source": "bin_music_viz_seqstate_play_score", "target": "bin_music_viz_instruments", "relation": "references", "confidence": "EXTRACTED", "source_file": "src/bin/music_viz.rs", "source_location": "L329", "weight": 1.0, "context": "parameter_type"}, {"source": "bin_music_viz_seqstate", "target": "bin_music_viz_seqstate_vbl_tick", "relation": "method", "confidence": "EXTRACTED", "source_file": "src/bin/music_viz.rs", "source_location": "L353", "weight": 1.0}, {"source": "bin_music_viz_seqstate_vbl_tick", "target": "bin_music_viz_instruments", "relation": "references", "confidence": "EXTRACTED", "source_file": "src/bin/music_viz.rs", "source_location": "L353", "weight": 1.0, "context": "parameter_type"}, {"source": "bin_music_viz_seqstate", "target": "bin_music_viz_seqstate_tick_voice", "relation": "method", "confidence": "EXTRACTED", "source_file": "src/bin/music_viz.rs", "source_location": "L363", "weight": 1.0}, {"source": "bin_music_viz_seqstate_tick_voice", "target": "bin_music_viz_instruments", "relation": "references", "confidence": "EXTRACTED", "source_file": "src/bin/music_viz.rs", "source_location": "L363", "weight": 1.0, "context": "parameter_type"}, {"source": "home_ddehaven_projects_faery_tale_rs_src_bin_music_viz_rs", "target": "bin_music_viz_synthcallback", "relation": "contains", "confidence": "EXTRACTED", "source_file": "src/bin/music_viz.rs", "source_location": "L440", "weight": 1.0}, {"source": "bin_music_viz_synthcallback", "target": "arc", "relation": "references", "confidence": "EXTRACTED", "source_file": "src/bin/music_viz.rs", "source_location": "L441", "weight": 1.0, "context": "field"}, {"source": "bin_music_viz_synthcallback", "target": "mutex", "relation": "references", "confidence": "EXTRACTED", "source_file": "src/bin/music_viz.rs", "source_location": "L441", "weight": 1.0, "context": "generic_arg"}, {"source": "bin_music_viz_synthcallback", "target": "bin_music_viz_seqstate", "relation": "references", "confidence": "EXTRACTED", "source_file": "src/bin/music_viz.rs", "source_location": "L441", "weight": 1.0, "context": "generic_arg"}, {"source": "bin_music_viz_synthcallback", "target": "bin_music_viz_instruments", "relation": "references", "confidence": "EXTRACTED", "source_file": "src/bin/music_viz.rs", "source_location": "L442", "weight": 1.0, "context": "field"}, {"source": "bin_music_viz_synthcallback", "target": "audiocallback", "relation": "implements", "confidence": "EXTRACTED", "source_file": "src/bin/music_viz.rs", "source_location": "L445", "weight": 1.0}, {"source": "bin_music_viz_synthcallback", "target": "bin_music_viz_synthcallback_callback", "relation": "method", "confidence": "EXTRACTED", "source_file": "src/bin/music_viz.rs", "source_location": "L446", "weight": 1.0}, {"source": "bin_music_viz_synthcallback_callback", "target": "audiostream", "relation": "references", "confidence": "EXTRACTED", "source_file": "src/bin/music_viz.rs", "source_location": "L446", "weight": 1.0, "context": "parameter_type"}, {"source": "home_ddehaven_projects_faery_tale_rs_src_bin_music_viz_rs", "target": "bin_music_viz_pitch_name", "relation": "contains", "confidence": "EXTRACTED", "source_file": "src/bin/music_viz.rs", "source_location": "L526", "weight": 1.0}, {"source": "bin_music_viz_pitch_name", "target": "string", "relation": "references", "confidence": "EXTRACTED", "source_file": "src/bin/music_viz.rs", "source_location": "L526", "weight": 1.0, "context": "return_type"}, {"source": "home_ddehaven_projects_faery_tale_rs_src_bin_music_viz_rs", "target": "bin_music_viz_scheduledevent", "relation": "contains", "confidence": "EXTRACTED", "source_file": "src/bin/music_viz.rs", "source_location": "L551", "weight": 1.0}, {"source": "bin_music_viz_scheduledevent", "target": "string", "relation": "references", "confidence": "EXTRACTED", "source_file": "src/bin/music_viz.rs", "source_location": "L554", "weight": 1.0, "context": "field"}, {"source": "home_ddehaven_projects_faery_tale_rs_src_bin_music_viz_rs", "target": "bin_music_viz_trackvis", "relation": "contains", "confidence": "EXTRACTED", "source_file": "src/bin/music_viz.rs", "source_location": "L558", "weight": 1.0}, {"source": "bin_music_viz_trackvis", "target": "vec", "relation": "references", "confidence": "EXTRACTED", "source_file": "src/bin/music_viz.rs", "source_location": "L559", "weight": 1.0, "context": "field"}, {"source": "bin_music_viz_trackvis", "target": "bin_music_viz_scheduledevent", "relation": "references", "confidence": "EXTRACTED", "source_file": "src/bin/music_viz.rs", "source_location": "L559", "weight": 1.0, "context": "generic_arg"}, {"source": "bin_music_viz_trackvis", "target": "bin_music_viz_trackvis_new", "relation": "method", "confidence": "EXTRACTED", "source_file": "src/bin/music_viz.rs", "source_location": "L567", "weight": 1.0}, {"source": "bin_music_viz_trackvis_new", "target": "track", "relation": "references", "confidence": "EXTRACTED", "source_file": "src/bin/music_viz.rs", "source_location": "L567", "weight": 1.0, "context": "parameter_type"}, {"source": "bin_music_viz_trackvis_new", "target": "self", "relation": "references", "confidence": "EXTRACTED", "source_file": "src/bin/music_viz.rs", "source_location": "L567", "weight": 1.0, "context": "return_type"}, {"source": "bin_music_viz_trackvis", "target": "bin_music_viz_trackvis_event_at", "relation": "method", "confidence": "EXTRACTED", "source_file": "src/bin/music_viz.rs", "source_location": "L637", "weight": 1.0}, {"source": "bin_music_viz_trackvis_event_at", "target": "option", "relation": "references", "confidence": "EXTRACTED", "source_file": "src/bin/music_viz.rs", "source_location": "L637", "weight": 1.0, "context": "return_type"}, {"source": "bin_music_viz_trackvis_event_at", "target": "bin_music_viz_scheduledevent", "relation": "references", "confidence": "EXTRACTED", "source_file": "src/bin/music_viz.rs", "source_location": "L637", "weight": 1.0, "context": "generic_arg"}, {"source": "home_ddehaven_projects_faery_tale_rs_src_bin_music_viz_rs", "target": "bin_music_viz_app", "relation": "contains", "confidence": "EXTRACTED", "source_file": "src/bin/music_viz.rs", "source_location": "L672", "weight": 1.0}, {"source": "bin_music_viz_app", "target": "songlibrary", "relation": "references", "confidence": "EXTRACTED", "source_file": "src/bin/music_viz.rs", "source_location": "L673", "weight": 1.0, "context": "field"}, {"source": "bin_music_viz_app", "target": "bin_music_viz_instruments", "relation": "references", "confidence": "EXTRACTED", "source_file": "src/bin/music_viz.rs", "source_location": "L674", "weight": 1.0, "context": "field"}, {"source": "bin_music_viz_app", "target": "bin_music_viz_trackvis", "relation": "references", "confidence": "EXTRACTED", "source_file": "src/bin/music_viz.rs", "source_location": "L676", "weight": 1.0, "context": "field"}, {"source": "bin_music_viz_app", "target": "arc", "relation": "references", "confidence": "EXTRACTED", "source_file": "src/bin/music_viz.rs", "source_location": "L680", "weight": 1.0, "context": "field"}, {"source": "bin_music_viz_app", "target": "mutex", "relation": "references", "confidence": "EXTRACTED", "source_file": "src/bin/music_viz.rs", "source_location": "L680", "weight": 1.0, "context": "generic_arg"}, {"source": "bin_music_viz_app", "target": "bin_music_viz_seqstate", "relation": "references", "confidence": "EXTRACTED", "source_file": "src/bin/music_viz.rs", "source_location": "L680", "weight": 1.0, "context": "generic_arg"}, {"source": "bin_music_viz_app", "target": "bin_music_viz_app_new", "relation": "method", "confidence": "EXTRACTED", "source_file": "src/bin/music_viz.rs", "source_location": "L684", "weight": 1.0}, {"source": "bin_music_viz_app_new", "target": "songlibrary", "relation": "references", "confidence": "EXTRACTED", "source_file": "src/bin/music_viz.rs", "source_location": "L684", "weight": 1.0, "context": "parameter_type"}, {"source": "bin_music_viz_app_new", "target": "bin_music_viz_instruments", "relation": "references", "confidence": "EXTRACTED", "source_file": "src/bin/music_viz.rs", "source_location": "L684", "weight": 1.0, "context": "parameter_type"}, {"source": "bin_music_viz_app_new", "target": "arc", "relation": "references", "confidence": "EXTRACTED", "source_file": "src/bin/music_viz.rs", "source_location": "L684", "weight": 1.0, "context": "parameter_type"}, {"source": "bin_music_viz_app_new", "target": "mutex", "relation": "references", "confidence": "EXTRACTED", "source_file": "src/bin/music_viz.rs", "source_location": "L684", "weight": 1.0, "context": "generic_arg"}, {"source": "bin_music_viz_app_new", "target": "bin_music_viz_seqstate", "relation": "references", "confidence": "EXTRACTED", "source_file": "src/bin/music_viz.rs", "source_location": "L684", "weight": 1.0, "context": "generic_arg"}, {"source": "bin_music_viz_app_new", "target": "self", "relation": "references", "confidence": "EXTRACTED", "source_file": "src/bin/music_viz.rs", "source_location": "L684", "weight": 1.0, "context": "return_type"}, {"source": "bin_music_viz_app", "target": "bin_music_viz_app_make_tracks", "relation": "method", "confidence": "EXTRACTED", "source_file": "src/bin/music_viz.rs", "source_location": "L703", "weight": 1.0}, {"source": "bin_music_viz_app_make_tracks", "target": "songlibrary", "relation": "references", "confidence": "EXTRACTED", "source_file": "src/bin/music_viz.rs", "source_location": "L703", "weight": 1.0, "context": "parameter_type"}, {"source": "bin_music_viz_app_make_tracks", "target": "bin_music_viz_trackvis", "relation": "references", "confidence": "EXTRACTED", "source_file": "src/bin/music_viz.rs", "source_location": "L703", "weight": 1.0, "context": "return_type"}, {"source": "bin_music_viz_app", "target": "bin_music_viz_app_auto_scale", "relation": "method", "confidence": "EXTRACTED", "source_file": "src/bin/music_viz.rs", "source_location": "L716", "weight": 1.0}, {"source": "bin_music_viz_app_auto_scale", "target": "bin_music_viz_trackvis", "relation": "references", "confidence": "EXTRACTED", "source_file": "src/bin/music_viz.rs", "source_location": "L716", "weight": 1.0, "context": "parameter_type"}, {"source": "bin_music_viz_app", "target": "bin_music_viz_app_switch_group", "relation": "method", "confidence": "EXTRACTED", "source_file": "src/bin/music_viz.rs", "source_location": "L731", "weight": 1.0}, {"source": "bin_music_viz_app", "target": "bin_music_viz_app_toggle_track", "relation": "method", "confidence": "EXTRACTED", "source_file": "src/bin/music_viz.rs", "source_location": "L755", "weight": 1.0}, {"source": "bin_music_viz_app", "target": "bin_music_viz_app_set_tempo", "relation": "method", "confidence": "EXTRACTED", "source_file": "src/bin/music_viz.rs", "source_location": "L761", "weight": 1.0}, {"source": "bin_music_viz_app", "target": "bin_music_viz_app_zoom_out", "relation": "method", "confidence": "EXTRACTED", "source_file": "src/bin/music_viz.rs", "source_location": "L767", "weight": 1.0}, {"source": "bin_music_viz_app", "target": "bin_music_viz_app_zoom_in", "relation": "method", "confidence": "EXTRACTED", "source_file": "src/bin/music_viz.rs", "source_location": "L770", "weight": 1.0}, {"source": "bin_music_viz_app", "target": "bin_music_viz_app_set_paused", "relation": "method", "confidence": "EXTRACTED", "source_file": "src/bin/music_viz.rs", "source_location": "L774", "weight": 1.0}, {"source": "bin_music_viz_app", "target": "bin_music_viz_app_step_tick", "relation": "method", "confidence": "EXTRACTED", "source_file": "src/bin/music_viz.rs", "source_location": "L782", "weight": 1.0}, {"source": "bin_music_viz_app", "target": "bin_music_viz_app_audio_pos", "relation": "method", "confidence": "EXTRACTED", "source_file": "src/bin/music_viz.rs", "source_location": "L791", "weight": 1.0}, {"source": "home_ddehaven_projects_faery_tale_rs_src_bin_music_viz_rs", "target": "bin_music_viz_instrument_name", "relation": "contains", "confidence": "EXTRACTED", "source_file": "src/bin/music_viz.rs", "source_location": "L804", "weight": 1.0}, {"source": "home_ddehaven_projects_faery_tale_rs_src_bin_music_viz_rs", "target": "bin_music_viz_render", "relation": "contains", "confidence": "EXTRACTED", "source_file": "src/bin/music_viz.rs", "source_location": "L811", "weight": 1.0}, {"source": "bin_music_viz_render", "target": "stdout", "relation": "references", "confidence": "EXTRACTED", "source_file": "src/bin/music_viz.rs", "source_location": "L811", "weight": 1.0, "context": "parameter_type"}, {"source": "bin_music_viz_render", "target": "bin_music_viz_app", "relation": "references", "confidence": "EXTRACTED", "source_file": "src/bin/music_viz.rs", "source_location": "L811", "weight": 1.0, "context": "parameter_type"}, {"source": "bin_music_viz_render", "target": "result", "relation": "references", "confidence": "EXTRACTED", "source_file": "src/bin/music_viz.rs", "source_location": "L811", "weight": 1.0, "context": "return_type"}, {"source": "home_ddehaven_projects_faery_tale_rs_src_bin_music_viz_rs", "target": "bin_music_viz_pad_or_clip", "relation": "contains", "confidence": "EXTRACTED", "source_file": "src/bin/music_viz.rs", "source_location": "L1002", "weight": 1.0}, {"source": "bin_music_viz_pad_or_clip", "target": "string", "relation": "references", "confidence": "EXTRACTED", "source_file": "src/bin/music_viz.rs", "source_location": "L1002", "weight": 1.0, "context": "return_type"}, {"source": "home_ddehaven_projects_faery_tale_rs_src_bin_music_viz_rs", "target": "bin_music_viz_main", "relation": "contains", "confidence": "EXTRACTED", "source_file": "src/bin/music_viz.rs", "source_location": "L1015", "weight": 1.0}, {"source": "bin_music_viz_main", "target": "result", "relation": "references", "confidence": "EXTRACTED", "source_file": "src/bin/music_viz.rs", "source_location": "L1015", "weight": 1.0, "context": "return_type"}, {"source": "bin_music_viz_main", "target": "box", "relation": "references", "confidence": "EXTRACTED", "source_file": "src/bin/music_viz.rs", "source_location": "L1015", "weight": 1.0, "context": "generic_arg"}, {"source": "bin_music_viz_main", "target": "error", "relation": "references", "confidence": "EXTRACTED", "source_file": "src/bin/music_viz.rs", "source_location": "L1015", "weight": 1.0, "context": "generic_arg"}, {"source": "bin_music_viz_instruments_load", "target": "bin_music_viz_instruments_parse", "relation": "calls", "context": "call", "confidence": "EXTRACTED", "source_file": "src/bin/music_viz.rs", "source_location": "L115", "weight": 1.0}, {"source": "bin_music_viz_seqstate_new", "target": "bin_music_viz_app_new", "relation": "calls", "context": "call", "confidence": "EXTRACTED", "source_file": "src/bin/music_viz.rs", "source_location": "L319", "weight": 1.0}, {"source": "bin_music_viz_seqstate_play_score", "target": "bin_music_viz_app_new", "relation": "calls", "context": "call", "confidence": "EXTRACTED", "source_file": "src/bin/music_viz.rs", "source_location": "L333", "weight": 1.0}, {"source": "bin_music_viz_seqstate_play_score", "target": "bin_music_viz_voice_set_instrument_slot", "relation": "calls", "context": "call", "confidence": "EXTRACTED", "source_file": "src/bin/music_viz.rs", "source_location": "L334", "weight": 1.0}, {"source": "bin_music_viz_seqstate_vbl_tick", "target": "bin_music_viz_seqstate_tick_voice", "relation": "calls", "context": "call", "confidence": "EXTRACTED", "source_file": "src/bin/music_viz.rs", "source_location": "L359", "weight": 1.0}, {"source": "bin_music_viz_seqstate_tick_voice", "target": "bin_music_viz_voice_step_envelope", "relation": "calls", "context": "call", "confidence": "EXTRACTED", "source_file": "src/bin/music_viz.rs", "source_location": "L365", "weight": 1.0}, {"source": "bin_music_viz_seqstate_tick_voice", "target": "bin_music_viz_voice_trigger_note", "relation": "calls", "context": "call", "confidence": "EXTRACTED", "source_file": "src/bin/music_viz.rs", "source_location": "L402", "weight": 1.0}, {"source": "bin_music_viz_seqstate_tick_voice", "target": "bin_music_viz_voice_silence", "relation": "calls", "context": "call", "confidence": "EXTRACTED", "source_file": "src/bin/music_viz.rs", "source_location": "L411", "weight": 1.0}, {"source": "bin_music_viz_seqstate_tick_voice", "target": "bin_music_viz_voice_set_instrument_slot", "relation": "calls", "context": "call", "confidence": "EXTRACTED", "source_file": "src/bin/music_viz.rs", "source_location": "L415", "weight": 1.0}, {"source": "bin_music_viz_synthcallback_callback", "target": "bin_music_viz_seqstate_vbl_tick", "relation": "calls", "context": "call", "confidence": "EXTRACTED", "source_file": "src/bin/music_viz.rs", "source_location": "L464", "weight": 1.0}, {"source": "bin_music_viz_synthcallback_callback", "target": "bin_music_viz_voice_mix_stereo", "relation": "calls", "context": "call", "confidence": "EXTRACTED", "source_file": "src/bin/music_viz.rs", "source_location": "L475", "weight": 1.0}, {"source": "bin_music_viz_trackvis_new", "target": "bin_music_viz_app_new", "relation": "calls", "context": "call", "confidence": "EXTRACTED", "source_file": "src/bin/music_viz.rs", "source_location": "L568", "weight": 1.0}, {"source": "bin_music_viz_trackvis_new", "target": "bin_music_viz_pitch_name", "relation": "calls", "context": "call", "confidence": "EXTRACTED", "source_file": "src/bin/music_viz.rs", "source_location": "L589", "weight": 1.0}, {"source": "bin_music_viz_app_new", "target": "bin_music_viz_app_make_tracks", "relation": "calls", "context": "call", "confidence": "EXTRACTED", "source_file": "src/bin/music_viz.rs", "source_location": "L690", "weight": 1.0}, {"source": "bin_music_viz_app_new", "target": "bin_music_viz_app_auto_scale", "relation": "calls", "context": "call", "confidence": "EXTRACTED", "source_file": "src/bin/music_viz.rs", "source_location": "L691", "weight": 1.0}, {"source": "bin_music_viz_app_make_tracks", "target": "bin_music_viz_app_new", "relation": "calls", "context": "call", "confidence": "EXTRACTED", "source_file": "src/bin/music_viz.rs", "source_location": "L706", "weight": 1.0}, {"source": "bin_music_viz_app_switch_group", "target": "bin_music_viz_app_make_tracks", "relation": "calls", "context": "call", "confidence": "EXTRACTED", "source_file": "src/bin/music_viz.rs", "source_location": "L736", "weight": 1.0}, {"source": "bin_music_viz_app_switch_group", "target": "bin_music_viz_app_auto_scale", "relation": "calls", "context": "call", "confidence": "EXTRACTED", "source_file": "src/bin/music_viz.rs", "source_location": "L737", "weight": 1.0}, {"source": "bin_music_viz_app_switch_group", "target": "bin_music_viz_app_new", "relation": "calls", "context": "call", "confidence": "EXTRACTED", "source_file": "src/bin/music_viz.rs", "source_location": "L741", "weight": 1.0}, {"source": "bin_music_viz_app_switch_group", "target": "bin_music_viz_seqstate_play_score", "relation": "calls", "context": "call", "confidence": "EXTRACTED", "source_file": "src/bin/music_viz.rs", "source_location": "L747", "weight": 1.0}, {"source": "bin_music_viz_app_step_tick", "target": "bin_music_viz_seqstate_vbl_tick", "relation": "calls", "context": "call", "confidence": "EXTRACTED", "source_file": "src/bin/music_viz.rs", "source_location": "L786", "weight": 1.0}, {"source": "bin_music_viz_render", "target": "bin_music_viz_pad_or_clip", "relation": "calls", "context": "call", "confidence": "EXTRACTED", "source_file": "src/bin/music_viz.rs", "source_location": "L835", "weight": 1.0}, {"source": "bin_music_viz_render", "target": "bin_music_viz_instrument_name", "relation": "calls", "context": "call", "confidence": "EXTRACTED", "source_file": "src/bin/music_viz.rs", "source_location": "L857", "weight": 1.0}, {"source": "bin_music_viz_render", "target": "bin_music_viz_trackvis_event_at", "relation": "calls", "context": "call", "confidence": "EXTRACTED", "source_file": "src/bin/music_viz.rs", "source_location": "L920", "weight": 1.0}, {"source": "bin_music_viz_main", "target": "bin_music_viz_app_new", "relation": "calls", "context": "call", "confidence": "EXTRACTED", "source_file": "src/bin/music_viz.rs", "source_location": "L1016", "weight": 1.0}, {"source": "bin_music_viz_main", "target": "bin_music_viz_instruments_load", "relation": "calls", "context": "call", "confidence": "EXTRACTED", "source_file": "src/bin/music_viz.rs", "source_location": "L1017", "weight": 1.0}, {"source": "bin_music_viz_main", "target": "bin_music_viz_seqstate_play_score", "relation": "calls", "context": "call", "confidence": "EXTRACTED", "source_file": "src/bin/music_viz.rs", "source_location": "L1062", "weight": 1.0}, {"source": "bin_music_viz_main", "target": "bin_music_viz_app_set_paused", "relation": "calls", "context": "call", "confidence": "EXTRACTED", "source_file": "src/bin/music_viz.rs", "source_location": "L1086", "weight": 1.0}, {"source": "bin_music_viz_main", "target": "bin_music_viz_app_step_tick", "relation": "calls", "context": "call", "confidence": "EXTRACTED", "source_file": "src/bin/music_viz.rs", "source_location": "L1090", "weight": 1.0}, {"source": "bin_music_viz_main", "target": "bin_music_viz_app_audio_pos", "relation": "calls", "context": "call", "confidence": "EXTRACTED", "source_file": "src/bin/music_viz.rs", "source_location": "L1095", "weight": 1.0}, {"source": "bin_music_viz_main", "target": "bin_music_viz_app_set_tempo", "relation": "calls", "context": "call", "confidence": "EXTRACTED", "source_file": "src/bin/music_viz.rs", "source_location": "L1096", "weight": 1.0}, {"source": "bin_music_viz_main", "target": "bin_music_viz_app_toggle_track", "relation": "calls", "context": "call", "confidence": "EXTRACTED", "source_file": "src/bin/music_viz.rs", "source_location": "L1104", "weight": 1.0}, {"source": "bin_music_viz_main", "target": "bin_music_viz_app_zoom_in", "relation": "calls", "context": "call", "confidence": "EXTRACTED", "source_file": "src/bin/music_viz.rs", "source_location": "L1117", "weight": 1.0}, {"source": "bin_music_viz_main", "target": "bin_music_viz_app_zoom_out", "relation": "calls", "context": "call", "confidence": "EXTRACTED", "source_file": "src/bin/music_viz.rs", "source_location": "L1120", "weight": 1.0}, {"source": "bin_music_viz_main", "target": "bin_music_viz_app_switch_group", "relation": "calls", "context": "call", "confidence": "EXTRACTED", "source_file": "src/bin/music_viz.rs", "source_location": "L1125", "weight": 1.0}, {"source": "bin_music_viz_main", "target": "bin_music_viz_render", "relation": "calls", "context": "call", "confidence": "EXTRACTED", "source_file": "src/bin/music_viz.rs", "source_location": "L1141", "weight": 1.0}], "raw_calls": [{"caller_nid": "bin_music_viz_instruments_parse", "callee": "iter_mut", "is_member_call": true, "source_file": "/home/ddehaven/projects/faery-tale-rs/src/bin/music_viz.rs", "source_location": "L121"}, {"caller_nid": "bin_music_viz_instruments_parse", "callee": "iter_mut", "is_member_call": true, "source_file": "/home/ddehaven/projects/faery-tale-rs/src/bin/music_viz.rs", "source_location": "L124"}, {"caller_nid": "bin_music_viz_instruments_parse", "callee": "iter_mut", "is_member_call": true, "source_file": "/home/ddehaven/projects/faery-tale-rs/src/bin/music_viz.rs", "source_location": "L131"}, {"caller_nid": "bin_music_viz_instruments_parse", "callee": "copy_from_slice", "is_member_call": true, "source_file": "/home/ddehaven/projects/faery-tale-rs/src/bin/music_viz.rs", "source_location": "L134"}, {"caller_nid": "bin_music_viz_voice_step_envelope", "callee": "saturating_add", "is_member_call": true, "source_file": "/home/ddehaven/projects/faery-tale-rs/src/bin/music_viz.rs", "source_location": "L240"}, {"caller_nid": "bin_music_viz_voice_mix_stereo", "callee": "iter_mut", "is_member_call": true, "source_file": "/home/ddehaven/projects/faery-tale-rs/src/bin/music_viz.rs", "source_location": "L273"}, {"caller_nid": "bin_music_viz_voice_mix_stereo", "callee": "iter_mut", "is_member_call": true, "source_file": "/home/ddehaven/projects/faery-tale-rs/src/bin/music_viz.rs", "source_location": "L273"}, {"caller_nid": "bin_music_viz_seqstate_play_score", "callee": "iter_mut", "is_member_call": true, "source_file": "/home/ddehaven/projects/faery-tale-rs/src/bin/music_viz.rs", "source_location": "L332"}, {"caller_nid": "bin_music_viz_seqstate_vbl_tick", "callee": "wrapping_add", "is_member_call": true, "source_file": "/home/ddehaven/projects/faery-tale-rs/src/bin/music_viz.rs", "source_location": "L357"}, {"caller_nid": "bin_music_viz_seqstate_tick_voice", "callee": "is_none", "is_member_call": true, "source_file": "/home/ddehaven/projects/faery-tale-rs/src/bin/music_viz.rs", "source_location": "L366"}, {"caller_nid": "bin_music_viz_seqstate_tick_voice", "callee": "wrapping_sub", "is_member_call": true, "source_file": "/home/ddehaven/projects/faery-tale-rs/src/bin/music_viz.rs", "source_location": "L374"}, {"caller_nid": "bin_music_viz_seqstate_tick_voice", "callee": "wrapping_sub", "is_member_call": true, "source_file": "/home/ddehaven/projects/faery-tale-rs/src/bin/music_viz.rs", "source_location": "L376"}, {"caller_nid": "bin_music_viz_seqstate_tick_voice", "callee": "wrapping_add", "is_member_call": true, "source_file": "/home/ddehaven/projects/faery-tale-rs/src/bin/music_viz.rs", "source_location": "L399"}, {"caller_nid": "bin_music_viz_seqstate_tick_voice", "callee": "wrapping_add", "is_member_call": true, "source_file": "/home/ddehaven/projects/faery-tale-rs/src/bin/music_viz.rs", "source_location": "L400"}, {"caller_nid": "bin_music_viz_seqstate_tick_voice", "callee": "wrapping_add", "is_member_call": true, "source_file": "/home/ddehaven/projects/faery-tale-rs/src/bin/music_viz.rs", "source_location": "L409"}, {"caller_nid": "bin_music_viz_seqstate_tick_voice", "callee": "unwrap_or", "is_member_call": true, "source_file": "/home/ddehaven/projects/faery-tale-rs/src/bin/music_viz.rs", "source_location": "L422"}, {"caller_nid": "bin_music_viz_synthcallback_callback", "callee": "put_data_i16", "is_member_call": true, "source_file": "/home/ddehaven/projects/faery-tale-rs/src/bin/music_viz.rs", "source_location": "L455"}, {"caller_nid": "bin_music_viz_synthcallback_callback", "callee": "floor", "is_member_call": true, "source_file": "/home/ddehaven/projects/faery-tale-rs/src/bin/music_viz.rs", "source_location": "L468"}, {"caller_nid": "bin_music_viz_synthcallback_callback", "callee": "clamp", "is_member_call": true, "source_file": "/home/ddehaven/projects/faery-tale-rs/src/bin/music_viz.rs", "source_location": "L509"}, {"caller_nid": "bin_music_viz_synthcallback_callback", "callee": "clamp", "is_member_call": true, "source_file": "/home/ddehaven/projects/faery-tale-rs/src/bin/music_viz.rs", "source_location": "L510"}, {"caller_nid": "bin_music_viz_synthcallback_callback", "callee": "put_data_i16", "is_member_call": true, "source_file": "/home/ddehaven/projects/faery-tale-rs/src/bin/music_viz.rs", "source_location": "L515"}, {"caller_nid": "bin_music_viz_pitch_name", "callee": "log2", "is_member_call": true, "source_file": "/home/ddehaven/projects/faery-tale-rs/src/bin/music_viz.rs", "source_location": "L536"}, {"caller_nid": "bin_music_viz_trackvis_new", "callee": "unwrap_or", "is_member_call": true, "source_file": "/home/ddehaven/projects/faery-tale-rs/src/bin/music_viz.rs", "source_location": "L618"}, {"caller_nid": "bin_music_viz_trackvis_event_at", "callee": "saturating_add", "is_member_call": true, "source_file": "/home/ddehaven/projects/faery-tale-rs/src/bin/music_viz.rs", "source_location": "L646"}, {"caller_nid": "bin_music_viz_trackvis_event_at", "callee": "partition_point", "is_member_call": true, "source_file": "/home/ddehaven/projects/faery-tale-rs/src/bin/music_viz.rs", "source_location": "L649"}, {"caller_nid": "bin_music_viz_trackvis_event_at", "callee": "saturating_add", "is_member_call": true, "source_file": "/home/ddehaven/projects/faery-tale-rs/src/bin/music_viz.rs", "source_location": "L659"}, {"caller_nid": "bin_music_viz_app_make_tracks", "callee": "group", "is_member_call": true, "source_file": "/home/ddehaven/projects/faery-tale-rs/src/bin/music_viz.rs", "source_location": "L704"}, {"caller_nid": "bin_music_viz_app_auto_scale", "callee": "unwrap_or", "is_member_call": true, "source_file": "/home/ddehaven/projects/faery-tale-rs/src/bin/music_viz.rs", "source_location": "L717"}, {"caller_nid": "bin_music_viz_app_switch_group", "callee": "is_none", "is_member_call": true, "source_file": "/home/ddehaven/projects/faery-tale-rs/src/bin/music_viz.rs", "source_location": "L732"}, {"caller_nid": "bin_music_viz_app_switch_group", "callee": "group", "is_member_call": true, "source_file": "/home/ddehaven/projects/faery-tale-rs/src/bin/music_viz.rs", "source_location": "L732"}, {"caller_nid": "bin_music_viz_app_switch_group", "callee": "group", "is_member_call": true, "source_file": "/home/ddehaven/projects/faery-tale-rs/src/bin/music_viz.rs", "source_location": "L739"}, {"caller_nid": "bin_music_viz_instrument_name", "callee": "unwrap_or", "is_member_call": true, "source_file": "/home/ddehaven/projects/faery-tale-rs/src/bin/music_viz.rs", "source_location": "L805"}, {"caller_nid": "bin_music_viz_instrument_name", "callee": "copied", "is_member_call": true, "source_file": "/home/ddehaven/projects/faery-tale-rs/src/bin/music_viz.rs", "source_location": "L805"}, {"caller_nid": "bin_music_viz_render", "callee": "saturating_sub", "is_member_call": true, "source_file": "/home/ddehaven/projects/faery-tale-rs/src/bin/music_viz.rs", "source_location": "L817"}, {"caller_nid": "bin_music_viz_render", "callee": "saturating_sub", "is_member_call": true, "source_file": "/home/ddehaven/projects/faery-tale-rs/src/bin/music_viz.rs", "source_location": "L850"}, {"caller_nid": "bin_music_viz_render", "callee": "saturating_sub", "is_member_call": true, "source_file": "/home/ddehaven/projects/faery-tale-rs/src/bin/music_viz.rs", "source_location": "L852"}, {"caller_nid": "bin_music_viz_render", "callee": "repeat", "is_member_call": true, "source_file": "/home/ddehaven/projects/faery-tale-rs/src/bin/music_viz.rs", "source_location": "L853"}, {"caller_nid": "bin_music_viz_render", "callee": "push_str", "is_member_call": true, "source_file": "/home/ddehaven/projects/faery-tale-rs/src/bin/music_viz.rs", "source_location": "L859"}, {"caller_nid": "bin_music_viz_render", "callee": "push_str", "is_member_call": true, "source_file": "/home/ddehaven/projects/faery-tale-rs/src/bin/music_viz.rs", "source_location": "L893"}, {"caller_nid": "bin_music_viz_render", "callee": "push_str", "is_member_call": true, "source_file": "/home/ddehaven/projects/faery-tale-rs/src/bin/music_viz.rs", "source_location": "L894"}, {"caller_nid": "bin_music_viz_render", "callee": "repeat", "is_member_call": true, "source_file": "/home/ddehaven/projects/faery-tale-rs/src/bin/music_viz.rs", "source_location": "L894"}, {"caller_nid": "bin_music_viz_render", "callee": "push_str", "is_member_call": true, "source_file": "/home/ddehaven/projects/faery-tale-rs/src/bin/music_viz.rs", "source_location": "L896"}, {"caller_nid": "bin_music_viz_render", "callee": "repeat", "is_member_call": true, "source_file": "/home/ddehaven/projects/faery-tale-rs/src/bin/music_viz.rs", "source_location": "L896"}, {"caller_nid": "bin_music_viz_render", "callee": "push_str", "is_member_call": true, "source_file": "/home/ddehaven/projects/faery-tale-rs/src/bin/music_viz.rs", "source_location": "L912"}, {"caller_nid": "bin_music_viz_render", "callee": "push_str", "is_member_call": true, "source_file": "/home/ddehaven/projects/faery-tale-rs/src/bin/music_viz.rs", "source_location": "L914"}, {"caller_nid": "bin_music_viz_render", "callee": "repeat", "is_member_call": true, "source_file": "/home/ddehaven/projects/faery-tale-rs/src/bin/music_viz.rs", "source_location": "L932"}, {"caller_nid": "bin_music_viz_render", "callee": "repeat", "is_member_call": true, "source_file": "/home/ddehaven/projects/faery-tale-rs/src/bin/music_viz.rs", "source_location": "L935"}, {"caller_nid": "bin_music_viz_render", "callee": "push_str", "is_member_call": true, "source_file": "/home/ddehaven/projects/faery-tale-rs/src/bin/music_viz.rs", "source_location": "L937"}, {"caller_nid": "bin_music_viz_render", "callee": "unsigned_abs", "is_member_call": true, "source_file": "/home/ddehaven/projects/faery-tale-rs/src/bin/music_viz.rs", "source_location": "L955"}, {"caller_nid": "bin_music_viz_render", "callee": "flush", "is_member_call": true, "source_file": "/home/ddehaven/projects/faery-tale-rs/src/bin/music_viz.rs", "source_location": "L998"}, {"caller_nid": "bin_music_viz_pad_or_clip", "callee": "count", "is_member_call": true, "source_file": "/home/ddehaven/projects/faery-tale-rs/src/bin/music_viz.rs", "source_location": "L1003"}, {"caller_nid": "bin_music_viz_pad_or_clip", "callee": "chars", "is_member_call": true, "source_file": "/home/ddehaven/projects/faery-tale-rs/src/bin/music_viz.rs", "source_location": "L1003"}, {"caller_nid": "bin_music_viz_pad_or_clip", "callee": "take", "is_member_call": true, "source_file": "/home/ddehaven/projects/faery-tale-rs/src/bin/music_viz.rs", "source_location": "L1005"}, {"caller_nid": "bin_music_viz_pad_or_clip", "callee": "chars", "is_member_call": true, "source_file": "/home/ddehaven/projects/faery-tale-rs/src/bin/music_viz.rs", "source_location": "L1005"}, {"caller_nid": "bin_music_viz_main", "callee": "join", "is_member_call": true, "source_file": "/home/ddehaven/projects/faery-tale-rs/src/bin/music_viz.rs", "source_location": "L1017"}, {"caller_nid": "bin_music_viz_main", "callee": "join", "is_member_call": true, "source_file": "/home/ddehaven/projects/faery-tale-rs/src/bin/music_viz.rs", "source_location": "L1019"}, {"caller_nid": "bin_music_viz_main", "callee": "unwrap_or", "is_member_call": true, "source_file": "/home/ddehaven/projects/faery-tale-rs/src/bin/music_viz.rs", "source_location": "L1024"}, {"caller_nid": "bin_music_viz_main", "callee": "and_then", "is_member_call": true, "source_file": "/home/ddehaven/projects/faery-tale-rs/src/bin/music_viz.rs", "source_location": "L1024"}, {"caller_nid": "bin_music_viz_main", "callee": "audio", "is_member_call": true, "source_file": "/home/ddehaven/projects/faery-tale-rs/src/bin/music_viz.rs", "source_location": "L1031"}, {"caller_nid": "bin_music_viz_main", "callee": "open_playback_stream", "is_member_call": true, "source_file": "/home/ddehaven/projects/faery-tale-rs/src/bin/music_viz.rs", "source_location": "L1042"}, {"caller_nid": "bin_music_viz_main", "callee": "resume", "is_member_call": true, "source_file": "/home/ddehaven/projects/faery-tale-rs/src/bin/music_viz.rs", "source_location": "L1049"}, {"caller_nid": "bin_music_viz_main", "callee": "unwrap_or_else", "is_member_call": true, "source_file": "/home/ddehaven/projects/faery-tale-rs/src/bin/music_viz.rs", "source_location": "L1053"}, {"caller_nid": "bin_music_viz_main", "callee": "group", "is_member_call": true, "source_file": "/home/ddehaven/projects/faery-tale-rs/src/bin/music_viz.rs", "source_location": "L1053"}, {"caller_nid": "bin_music_viz_main", "callee": "group", "is_member_call": true, "source_file": "/home/ddehaven/projects/faery-tale-rs/src/bin/music_viz.rs", "source_location": "L1055"}, {"caller_nid": "bin_music_viz_main", "callee": "saturating_sub", "is_member_call": true, "source_file": "/home/ddehaven/projects/faery-tale-rs/src/bin/music_viz.rs", "source_location": "L1100"}]}